funcnodes_webcam/__init__.py
funcnodes_webcam/controller.py
funcnodes_webcam/webcam_worker.py
funcnodes_webcam/react_plugin/index.iife.js
funcnodes_webcam/utils/__init__.py
funcnodes_webcam-1.0.0.dist-info/METADATA
funcnodes_webcam-1.0.0.dist-info/WHEEL
funcnodes_webcam-1.0.0.dist-info/entry_points.txt
funcnodes_webcam-1.0.0.dist-info/licenses/LICENSE
funcnodes_webcam-1.0.0.dist-info/RECORD
