Metadata-Version: 2.4
Name: funcnodes-webcam
Version: 1.0.0
Project-URL: homepage, https://github.com/Linkdlab/funcnodes_webcam
Project-URL: source, https://github.com/Linkdlab/funcnodes_webcam
Project-URL: tracker, https://github.com/Linkdlab/funcnodes_webcam/issues
Project-URL: download, https://pypi.org/project/funcnodes-webcam/#files
Author-email: Julian Kimmig <julian.kimmig@gmx.net>
License-Expression: AGPL-3.0
License-File: LICENSE
Requires-Python: >=3.11
Requires-Dist: funcnodes-opencv>=0.2.17
Requires-Dist: funcnodes-worker>=1.0.0
Requires-Dist: funcnodes>=1.0.0
